bvg_python/__init__.py
bvg_python/bvg.py
tests/__init__.py
tests/test_bvg.py
bvg_python-1.0.4.dist-info/LICENSE
bvg_python-1.0.4.dist-info/METADATA
bvg_python-1.0.4.dist-info/WHEEL
bvg_python-1.0.4.dist-info/top_level.txt
bvg_python-1.0.4.dist-info/RECORD
