Metadata-Version: 2.1
Name: bvg-python
Version: 1.0.4
Summary: Python wrapper for the BVG (Berliner Verkehrsbetriebe) public transportation REST API
Home-page: https://github.com/tlieshoff/bvg-python
Author: Tobias Lieshoff
Author-email: me@tobias-lieshoff.de
Classifier: Programming Language :: Python :: 3
Classifier: License :: OSI Approved :: MIT License
Classifier: Operating System :: OS Independent
Requires-Python: >=3.6
License-File: LICENSE
Requires-Dist: requests
